ucampurestorage/__init__.py
ucampurestorage/__main__.py
ucampurestorage/lib/__init__.py
ucampurestorage/lib/httpclient.py
ucampurestorage/lib/options.py
ucampurestorage/lib/process.py
ucampurestorage/lib/pureconnect.py
ucampurestorage/lib/tokencreater.py
ucampurestorage/tests/__init__.py
ucampurestorage/tests/test_httpclient.py
ucampurestorage/tests/test_process.py
ucampurestorage/tests/test_pureconnection.py
ucampurestorage/tests/test_tasks.py
ucampurestorage/tests/test_tokencreater.py
ucampurestorage-1.2.8.data/scripts/pure_clone_volume
ucampurestorage-1.2.8.data/scripts/pure_create_snapshot
ucampurestorage-1.2.8.data/scripts/pure_create_volume
ucampurestorage-1.2.8.data/scripts/pure_delete_volume
ucampurestorage-1.2.8.data/scripts/pure_eradicate_destroyed_volume
ucampurestorage-1.2.8.data/scripts/pure_eradicate_volume
ucampurestorage-1.2.8.data/scripts/pure_expire_snapshot_deletion
ucampurestorage-1.2.8.data/scripts/pure_map_volume
ucampurestorage-1.2.8.data/scripts/pure_record_destroyed_volume
ucampurestorage-1.2.8.data/scripts/pure_relabel_volume
ucampurestorage-1.2.8.data/scripts/pure_replace_volume
ucampurestorage-1.2.8.data/scripts/pure_unmap_volume
ucampurestorage-1.2.8.dist-info/LICENSE
ucampurestorage-1.2.8.dist-info/METADATA
ucampurestorage-1.2.8.dist-info/WHEEL
ucampurestorage-1.2.8.dist-info/entry_points.txt
ucampurestorage-1.2.8.dist-info/top_level.txt
ucampurestorage-1.2.8.dist-info/RECORD
