Metadata-Version: 2.1
Name: ucampurestorage
Version: 1.2.8
Summary: Pure Storage module for the utilization in Cambridge University
Author-email: Ishan Mahajan <imahajan0007@gmail.com>
Classifier: Programming Language :: Python :: 3
Classifier: License :: OSI Approved :: MIT License
Requires-Python: >=3.8
License-File: LICENSE
Requires-Dist: requests ==2.30.0
Requires-Dist: pyjwt[crypto]
Requires-Dist: paramiko ==3.1.0
Requires-Dist: distro ==1.8.0
Requires-Dist: importlib-metadata ; python_version >= "3.10"
